sub_tools/__init__.py
sub_tools/main.py
sub_tools/transcribe.py
sub_tools/arguments/__init__.py
sub_tools/arguments/env_default.py
sub_tools/arguments/parser.py
sub_tools/intelligence/__init__.py
sub_tools/intelligence/client.py
sub_tools/media/__init__.py
sub_tools/media/converter.py
sub_tools/media/info.py
sub_tools/media/segmenter.py
sub_tools/subtitles/combiner.py
sub_tools/subtitles/serializer.py
sub_tools/subtitles/validator.py
sub_tools/system/__init__.py
sub_tools/system/console.py
sub_tools/system/directory.py
sub_tools/system/language.py
sub_tools/system/logger.py
sub_tools/system/measure.py
sub_tools/system/rate_limiter.py
sub_tools-0.7.1.dist-info/METADATA
sub_tools-0.7.1.dist-info/WHEEL
sub_tools-0.7.1.dist-info/entry_points.txt
sub_tools-0.7.1.dist-info/licenses/LICENSE
sub_tools-0.7.1.dist-info/RECORD
