Metadata-Version: 2.4
Name: sub-tools
Version: 0.7.1
Summary: A robust Python toolkit powered by Google's Gemini API for converting video content into accurate, multilingual subtitles.
License-File: LICENSE
Requires-Python: >=3.10
Requires-Dist: audioop-lts>=0.2.1; python_version >= '3.13'
Requires-Dist: openai>=1.65.4
Requires-Dist: pycountry>=24.6.1
Requires-Dist: pydub>=0.25.1
Requires-Dist: pysrt>=1.1.2
Requires-Dist: pytest-asyncio>=0.23.5
Requires-Dist: pytest>=8.3.4
Requires-Dist: python-ffmpeg>=2.0.12
Requires-Dist: rich>=13.9.4
Requires-Dist: silero-vad>=5.1.2
Requires-Dist: soundfile>=0.13.1
